AUTHORS
LICENSE
MANIFEST.in
README.rst
setup.py
tests.py
wsgi_party.py
wsgi_party.egg-info/PKG-INFO
wsgi_party.egg-info/SOURCES.txt
wsgi_party.egg-info/dependency_links.txt
wsgi_party.egg-info/not-zip-safe
wsgi_party.egg-info/requires.txt
wsgi_party.egg-info/top_level.txt